litescript/__init__.py
litescript/data_science.py
litescript/logging_module.py
litescript/scripting.py
litescript/vis_utils.py
litescript-0.0.3.dist-info/AUTHORS.rst
litescript-0.0.3.dist-info/LICENSE
litescript-0.0.3.dist-info/METADATA
litescript-0.0.3.dist-info/WHEEL
litescript-0.0.3.dist-info/top_level.txt
litescript-0.0.3.dist-info/RECORD
