Metadata-Version: 2.1
Name: litescript
Version: 0.0.3
Summary: Utility package for streamlined Python scripts with logging, common imports, and essential utilities
Author-email: Somesh Fengade <someshfengde@gmail.com>
Maintainer-email: Somesh Fengade <someshfengde@gmail.com>
License: MIT license
Project-URL: bugs, https://github.com/someshfengde/litescript/issues
Project-URL: changelog, https://github.com/someshfengde/litescript/blob/master/changelog.md
Project-URL: homepage, https://github.com/someshfengde/litescript
License-File: LICENSE
License-File: AUTHORS.rst
Requires-Dist: tqdm
Requires-Dist: colorlog
Requires-Dist: pyyaml
Requires-Dist: rich
Requires-Dist: numpy
Requires-Dist: pandas
Requires-Dist: plotly
Requires-Dist: matplotlib
Provides-Extra: dev
Requires-Dist: coverage ; extra == 'dev'
Requires-Dist: mypy ; extra == 'dev'
Requires-Dist: pytest ; extra == 'dev'
Requires-Dist: ruff ; extra == 'dev'
